urltotext/ContentFinder.py
urltotext/__init__.py
urltotext-0.3.0.dist-info/LICENSE
urltotext-0.3.0.dist-info/METADATA
urltotext-0.3.0.dist-info/WHEEL
urltotext-0.3.0.dist-info/top_level.txt
urltotext-0.3.0.dist-info/RECORD
