Metadata-Version: 2.1
Name: urltotext
Version: 0.3.0
Summary: A light weight library that takes in a url and extracts any readable text in it.
Home-page: https://github.com/ChinmayShrivastava/url2text
Author: Chinmay Shrivastava
Author-email: cshrivastava99@gmail.com
License: GPLv3
Classifier: Development Status :: 3 - Alpha
Classifier: Intended Audience :: Developers
Classifier: License :: OSI Approved :: GNU General Public License v3 (GPLv3)
Classifier: Programming Language :: Python :: 3
Classifier: Environment :: MacOS X
Classifier: Environment :: Win32 (MS Windows)
Classifier: Environment :: X11 Applications
License-File: LICENSE
Requires-Dist: requests
Requires-Dist: bs4
Requires-Dist: langdetect
Requires-Dist: selenium
